building_footprint_segmentation/__init__.py
building_footprint_segmentation/segmentation.py
building_footprint_segmentation/trainer.py
building_footprint_segmentation/helpers/__init__.py
building_footprint_segmentation/helpers/callbacks.py
building_footprint_segmentation/helpers/metrics.py
building_footprint_segmentation/helpers/normalizer.py
building_footprint_segmentation/helpers/schedular.py
building_footprint_segmentation/modules/__init__.py
building_footprint_segmentation/modules/dan.py
building_footprint_segmentation/modules/gcn.py
building_footprint_segmentation/modules/se.py
building_footprint_segmentation/modules/spatial_pooling.py
building_footprint_segmentation/modules/sub_pixel.py
building_footprint_segmentation/seg/__init__.py
building_footprint_segmentation/seg/base_criterion.py
building_footprint_segmentation/seg/base_factory.py
building_footprint_segmentation/seg/base_loader.py
building_footprint_segmentation/seg/binary/__init__.py
building_footprint_segmentation/seg/binary/criterion.py
building_footprint_segmentation/seg/binary/factory.py
building_footprint_segmentation/seg/binary/loader.py
building_footprint_segmentation/seg/binary/metrics.py
building_footprint_segmentation/seg/binary/models/__init__.py
building_footprint_segmentation/seg/binary/models/albunet.py
building_footprint_segmentation/seg/binary/models/dlinknet.py
building_footprint_segmentation/seg/binary/models/mfrn.py
building_footprint_segmentation/seg/binary/models/refinenet.py
building_footprint_segmentation/seg/binary/models/refinenet_lite.py
building_footprint_segmentation/utils/__init__.py
building_footprint_segmentation/utils/date_time.py
building_footprint_segmentation/utils/operations.py
building_footprint_segmentation/utils/py_network.py
building_footprint_segmentation-0.2.4.dist-info/LICENSE
building_footprint_segmentation-0.2.4.dist-info/METADATA
building_footprint_segmentation-0.2.4.dist-info/WHEEL
building_footprint_segmentation-0.2.4.dist-info/top_level.txt
building_footprint_segmentation-0.2.4.dist-info/RECORD
