Metadata-Version: 2.1
Name: building-footprint-segmentation
Version: 0.2.4
Summary: Building footprint segmentation from satellite and aerial imagery
Home-page: https://github.com/fuzailpalnak/building-footprint-segmentation
Author: Fuzail Palnak
Author-email: fuzailpalnak@gmail.com
Keywords: Deep Learning,CNN,Semantic Segmentation,Building Footprint Extraction
Classifier: Programming Language :: Python :: 3
Classifier: License :: OSI Approved :: MIT License
Classifier: Topic :: Software Development :: Libraries
Classifier: Topic :: Software Development :: Libraries :: Python Modules
Classifier: Intended Audience :: Developers
Classifier: Operating System :: OS Independent
Requires-Python: ~=3.3
License-File: LICENSE
